mycalc/calculator.py
m0v3m1n_Calc_Prac-0.0.1.dist-info/METADATA
m0v3m1n_Calc_Prac-0.0.1.dist-info/WHEEL
m0v3m1n_Calc_Prac-0.0.1.dist-info/top_level.txt
m0v3m1n_Calc_Prac-0.0.1.dist-info/RECORD
