Metadata-Version: 2.1
Name: m0v3m1n-Calc-Prac
Version: 0.0.1
Summary: OSS_Dev Practice - Calculator
Home-page: https://github.com/m0v3m1n/m0v3m1n_Calc_Prac
Download-URL: https://github.com/m0v3m1n/m0v3m1n_Calc_Prac
Author: DMLee
License: UNKNOWN
Platform: UNKNOWN
Classifier: Programming Language :: Python :: 3
